fluxion_ai/__init__.py
fluxion_ai/core/__init__.py
fluxion_ai/core/agents/__init__.py
fluxion_ai/core/agents/agent.py
fluxion_ai/core/agents/coordination_agent.py
fluxion_ai/core/agents/delegation_agent.py
fluxion_ai/core/agents/llm_agent.py
fluxion_ai/core/agents/planning_agent.py
fluxion_ai/core/modules/__init__.py
fluxion_ai/core/modules/api_module.py
fluxion_ai/core/modules/ir_module.py
fluxion_ai/core/modules/llm_modules.py
fluxion_ai/core/registry/__init__.py
fluxion_ai/core/registry/agent_delegation_registry.py
fluxion_ai/core/registry/agent_registry.py
fluxion_ai/core/registry/tool_registry.py
fluxion_ai/models/__init__.py
fluxion_ai/models/message_model.py
fluxion_ai/models/plan_model.py
fluxion_ai/modules/__init__.py
fluxion_ai/modules/community_modules.py
fluxion_ai/modules/contextual_response.py
fluxion_ai/modules/rag_module.py
fluxion_ai/perception/__init__.py
fluxion_ai/perception/perception.py
fluxion_ai/prebuilt_agents/__init__.py
fluxion_ai/prebuilt_agents/chatbot.py
fluxion_ai/utils/__init__.py
fluxion_ai/utils/audio_utils.py
fluxion_ai/utils/loggers.py
fluxion_ai/utils/retry.py
fluxion_ai/workflows/__init__.py
fluxion_ai/workflows/abstract_workflow.py
fluxion_ai/workflows/agent_node.py
fluxion_ai/workflows/flyte_adapter.py
fluxion_ai/workflows/node.py
fluxion_ai/workflows/workflow_progress_tracker.py
fluxion_ai_python-1.1.1.dist-info/LICENSE
fluxion_ai_python-1.1.1.dist-info/METADATA
fluxion_ai_python-1.1.1.dist-info/WHEEL
fluxion_ai_python-1.1.1.dist-info/top_level.txt
fluxion_ai_python-1.1.1.dist-info/RECORD
