Metadata-Version: 2.2
Name: fluxion-ai-python
Version: 1.1.1
Summary: A framework for orchestrating flow-based agentic workflows using LLMs.
Home-page: https://github.com/ymitiku/fluxion
Author: Mitiku Yohannes
Author-email: se.mitiku.yohannes@gmail.com
License: Apache License 2.0
Classifier: Development Status :: 5 - Production/Stable
Classifier: Intended Audience :: Developers
Classifier: License :: OSI Approved :: Apache Software License
Classifier: Programming Language :: Python :: 3.10
Classifier: Programming Language :: Python :: 3.11
Classifier: Topic :: Software Development :: Libraries
Classifier: Topic :: Scientific/Engineering :: Artificial Intelligence
Requires-Python: >=3.8
License-File: LICENSE
Requires-Dist: chromadb==0.3.25
Requires-Dist: docstring_parser==0.16
Requires-Dist: faiss-cpu==1.8.0
Requires-Dist: flytekit==1.13.15
Requires-Dist: Pillow==10.4.0
Requires-Dist: speechrecognition==3.8.1
Requires-Dist: gtts
Requires-Dist: playsound
Requires-Dist: numpy==1.26.0
Requires-Dist: graphviz==0.20.3
Dynamic: author
Dynamic: author-email
Dynamic: classifier
Dynamic: description
Dynamic: description-content-type
Dynamic: home-page
Dynamic: license
Dynamic: requires-dist
Dynamic: requires-python
Dynamic: summary
